kashgari/__init__.py
kashgari/__version__.py
kashgari/corpus.py
kashgari/generators.py
kashgari/logger.py
kashgari/macros.py
kashgari/types.py
kashgari/callbacks/__init__.py
kashgari/callbacks/eval_callBack.py
kashgari/callbacks/save_callback.py
kashgari/embeddings/__init__.py
kashgari/embeddings/abc_embedding.py
kashgari/embeddings/bare_embedding.py
kashgari/embeddings/bert_embedding.py
kashgari/embeddings/transformer_embedding.py
kashgari/embeddings/word_embedding.py
kashgari/layers/__init__.py
kashgari/layers/behdanau_attention.py
kashgari/layers/conditional_random_field.py
kashgari/metrics/__init__.py
kashgari/metrics/multi_label_classification.py
kashgari/metrics/sequence_labeling.py
kashgari/processors/__init__.py
kashgari/processors/abc_processor.py
kashgari/processors/class_processor.py
kashgari/processors/sequence_processor.py
kashgari/processors/tools.py
kashgari/tasks/__init__.py
kashgari/tasks/abs_task_model.py
kashgari/tasks/classification/__init__.py
kashgari/tasks/classification/abc_model.py
kashgari/tasks/classification/bi_gru_model.py
kashgari/tasks/classification/bi_lstm_model.py
kashgari/tasks/classification/cnn_attention_model.py
kashgari/tasks/classification/cnn_gru_model.py
kashgari/tasks/classification/cnn_lstm_model.py
kashgari/tasks/classification/cnn_model.py
kashgari/tasks/labeling/__init__.py
kashgari/tasks/labeling/abc_model.py
kashgari/tasks/labeling/bi_gru_crf_model.py
kashgari/tasks/labeling/bi_gru_model.py
kashgari/tasks/labeling/bi_lstm_crf_model.py
kashgari/tasks/labeling/bi_lstm_model.py
kashgari/tasks/labeling/cnn_lstm_model.py
kashgari/tasks/seq2seq/__init__.py
kashgari/tasks/seq2seq/model.py
kashgari/tasks/seq2seq/decoder/__init__.py
kashgari/tasks/seq2seq/decoder/att_gru_decoder.py
kashgari/tasks/seq2seq/decoder/gru_decoder.py
kashgari/tasks/seq2seq/encoder/__init__.py
kashgari/tasks/seq2seq/encoder/gru_encoder.py
kashgari/tokenizers/__init__.py
kashgari/tokenizers/base_tokenizer.py
kashgari/tokenizers/bert_tokenizer.py
kashgari-2.0.2.dist-info/LICENSE
kashgari-2.0.2.dist-info/METADATA
kashgari-2.0.2.dist-info/WHEEL
kashgari-2.0.2.dist-info/top_level.txt
kashgari-2.0.2.dist-info/RECORD
