Metadata-Version: 2.1
Name: kashgari
Version: 2.0.2
Summary: Simple, Keras-powered multilingual NLP framework, allows you to build your models in 5 minutes for named entity recognition (NER), part-of-speech tagging (PoS) and text classification tasks. Includes BERT, GPT-2 and word2vec embedding.
Home-page: https://github.com/BrikerMan/Kashgari
Author: BrikerMan
Author-email: eliyar917@gmail.com
License: Apache License 2.0
Platform: UNKNOWN
Classifier: License :: OSI Approved :: Apache Software License
Classifier: Programming Language :: Python :: 3.6
Classifier: Programming Language :: Python :: Implementation :: CPython
Classifier: Programming Language :: Python :: Implementation :: PyPy
Requires-Python: >3.6
License-File: LICENSE
Requires-Dist: numpy (>=1.18.1)
Requires-Dist: gensim (<4.0.0,>=3.8.1)
Requires-Dist: pandas (>=1.0.1)
Requires-Dist: tqdm
Requires-Dist: bert4keras (>=0.9.1)
Requires-Dist: scikit-learn (>=0.21.1)
